micro_client/__init__.py
micro_client/common.py
micro_client/registry/__init__.py
micro_client/registry/consulregistry.py
micro_client/registry/etcdregistry.py
micro_client-1.0.1.dist-info/LICENSE
micro_client-1.0.1.dist-info/METADATA
micro_client-1.0.1.dist-info/WHEEL
micro_client-1.0.1.dist-info/top_level.txt
micro_client-1.0.1.dist-info/RECORD
