Metadata-Version: 2.1
Name: micro-client
Version: 1.0.1
Summary: Python 3 resolver for go-micro grpc services.
Home-page: https://github.com/zhuleixiao6666/python-micro_client
Author: zhuleixiao
Author-email: zhuleixiao666@gmail.com
License: UNKNOWN
Platform: UNKNOWN
Classifier: Programming Language :: Python :: 3
Classifier: License :: OSI Approved :: MIT License
Classifier: Operating System :: OS Independent
Requires-Dist: grpcio-tools (==1.27.2)
Requires-Dist: etcd3 (==0.12.0)
Requires-Dist: requests
Provides-Extra: doc
Requires-Dist: Sphinx (==1.7.0) ; extra == 'doc'
Provides-Extra: qa
Requires-Dist: flake8 (==3.5.0) ; extra == 'qa'
